organage/OrganAge.py
organage/__init__.py
organage/pycounts.py
organage-0.1.0.dist-info/LICENSE
organage-0.1.0.dist-info/WHEEL
organage-0.1.0.dist-info/METADATA
organage-0.1.0.dist-info/RECORD
