Metadata-Version: 2.1
Name: organage
Version: 0.1.0
Summary: A package to pestimate organ-specific biological age using SomaScan plasma proteomics data
License: MIT
Author: Hamilton Oh
Requires-Python: >=3.9,<4.0
Classifier: License :: OSI Approved :: MIT License
Classifier: Programming Language :: Python :: 3
Classifier: Programming Language :: Python :: 3.9
Classifier: Programming Language :: Python :: 3.10
Classifier: Programming Language :: Python :: 3.11
